caidin/__init__.py
caidin/caidin.py
caidin/algorithms/__init__.py
caidin/algorithms/collaborative_filtering.py
caidin/algorithms/content_based.py
caidin/algorithms/recommendation_engine.py
caidin-0.0.1.dist-info/METADATA
caidin-0.0.1.dist-info/WHEEL
caidin-0.0.1.dist-info/top_level.txt
caidin-0.0.1.dist-info/RECORD
