Metadata-Version: 2.1
Name: caidin
Version: 0.0.1
Summary: An open-source recommendation engine library in Python
Home-page: https://github.com/netesy/caidin
Author: Emmanuel Olisah
Author-email: Emmanuel Olisah <manuelolisah@gmail.com>
Project-URL: Documentation, https://github.com/netesy/caidin/docs
Project-URL: Source Code, https://github.com/netesy/caidin
Project-URL: Bug Tracker, https://github.com/netesy/caidin/issues
Keywords: recommendation,engine,content-based,collaborative filtering
Classifier: Development Status :: 3 - Alpha
Classifier: Programming Language :: Python :: 3
Classifier: License :: OSI Approved :: MIT License
Classifier: Operating System :: OS Independent
Requires-Python: >=3.6
